Workbook

Sheet 前提条件
A1: カフェ ひだまり 収支計画の前提条件
A2: 黄色のセルだけ書き換えてください。ほかのシートの数字とグラフが自動で計算し直されます（店名・数字はすべて架空）
A4: 項目 | B4: 1年目 | C4: 2年目 | D4: 3年目 | E4: 単位 | F4: メモ
A5: 平日の営業日数（月） | B5: 18 | C5: 18 | D5: 18 | E5: 日 | F5: 定休日は月2日
A6: 土日祝の営業日数（月） | B6: 7 | C6: 7 | D6: 7 | E6: 日
A7: 平日の1日の客数 | B7: 50 | C7: 60 | D7: 66 | E7: 人 | F7: 朝の在宅ワーク・子育て世代
A8: 土日祝の1日の客数 | B8: 68 | C8: 78 | D8: 88 | E8: 人 | F8: 家族連れ・焼き菓子の持ち帰り
A9: 平日の客単価 | B9: 1000 | C9: 1000 | D9: 1000 | E9: 円 | F9: ドリンク＋焼き菓子
A10: 土日祝の客単価 | B10: 1200 | C10: 1200 | D10: 1200 | E10: 円 | F10: ランチセット・持ち帰りが増える
A11: 原価率（売上に対する材料費） | B11: 0.3 | C11: 0.3 | D11: 0.3 | F11: 自家焙煎で豆の原価をおさえる
A12: アルバイトの時給 | B12: 1100 | C12: 1100 | D12: 1100 | E12: 円
A13: アルバイトの時間（月） | B13: 260 | C13: 380 | D13: 420 | E13: 時間 | F13: 1年目は店主中心で回す
A14: 家賃（月） | B14: 250000 | C14: 250000 | D14: 250000 | E14: 円 | F14: 18席・1階路面
A15: 水道光熱費（売上に対する割合） | B15: 0.05 | C15: 0.05 | D15: 0.05
A16: その他の経費（月） | B16: 80000 | C16: 80000 | D16: 80000 | E16: 円 | F16: 消耗品・通信・広告・保険など
A18: 開業資金と借入
A19: 物件取得費（保証金・仲介料など） | B19: 1500000 | E19: 円
A20: 内装工事 | B20: 3500000 | E20: 円
A21: 厨房機器（焙煎機・エスプレッソマシンなど） | B21: 2000000 | E21: 円
A22: 家具・食器などの備品 | B22: 500000 | E22: 円
A23: 運転資金（開店直後の仕入れ・家賃など） | B23: 1500000 | E23: 円 | F23: 売上が安定するまでの備え
A24: 自己資金 | B24: 3000000 | E24: 円
A25: 日本政策金融公庫からの借入 | B25: 6000000 | E25: 円
A26: 借入の年利 | B26: 0.025 | F26: 見本用の目安
A27: 返済期間 | B27: 84 | E27: か月 | F27: 7年・元金均等
A28: 設備の償却年数（内装・機器・備品） | B28: 8 | E28: 年 | F28: 見本では8年でならす
A29: 店主の生活費（月） | B29: 220000 | E29: 円 | F29: 手元に残るお金と比べる
A30: 開店 | B30: 2027年4月

Sheet 3年間の収支
A1: 3年間の収支計画
A2: 1年目は月別シートの合計、2・3年目は前提条件から計算（季節の係数の合計が12なので年の合計は同じ考え方）
A4: 項目 | B4: 1年目 | C4: 2年目 | D4: 3年目
A5: 売上 | B5: ='1年目の月別'!N6 | C5: =ROUND((前提条件!$C$5*前提条件!$C$7*前提条件!$C$9+前提条件!$C$6*前提条件!$C$8*前提条件!$C$10)*12,0) | D5: =ROUND((前提条件!$D$5*前提条件!$D$7*前提条件!$D$9+前提条件!$D$6*前提条件!$D$8*前提条件!$D$10)*12,0)
A6: 材料費（原価） | B6: ='1年目の月別'!N7 | C6: =ROUND(C5*前提条件!$C$11,0) | D6: =ROUND(D5*前提条件!$D$11,0)
A7: 粗利 | B7: ='1年目の月別'!N8 | C7: =C5-C6 | D7: =D5-D6
A8: アルバイト人件費 | B8: ='1年目の月別'!N9 | C8: =前提条件!$C$12*前提条件!$C$13*12 | D8: =前提条件!$D$12*前提条件!$D$13*12
A9: 家賃 | B9: ='1年目の月別'!N10 | C9: =前提条件!$C$14*12 | D9: =前提条件!$D$14*12
A10: 水道光熱費 | B10: ='1年目の月別'!N11 | C10: =ROUND(C5*前提条件!$C$15,0) | D10: =ROUND(D5*前提条件!$D$15,0)
A11: その他の経費 | B11: ='1年目の月別'!N12 | C11: =前提条件!$C$16*12 | D11: =前提条件!$D$16*12
A12: 減価償却費 | B12: ='1年目の月別'!N13 | C12: ='1年目の月別'!$N$13 | D12: ='1年目の月別'!$N$13
A13: 支払利息 | B13: ='1年目の月別'!N14 | C13: =SUMIF(返済表!$B$4:$B$87,2,返済表!$E$4:$E$87) | D13: =SUMIF(返済表!$B$4:$B$87,3,返済表!$E$4:$E$87)
A14: 経費の合計 | B14: ='1年目の月別'!N15 | C14: =SUM(C8:C13) | D14: =SUM(D8:D13)
A15: 利益 | B15: ='1年目の月別'!N16 | C15: =C7-C14 | D15: =D7-D14
A16: 利益率 | B16: =B15/B5 | C16: =C15/C5 | D16: =D15/D5
A18: 手元に残るお金（返済後） | B18: 1年目 | C18: 2年目 | D18: 3年目
A19: 利益＋減価償却費 | B19: =B15+B12 | C19: =C15+C12 | D19: =D15+D12
A20: 借入の元金返済 | B20: =SUMIF(返済表!$B$4:$B$87,1,返済表!$D$4:$D$87) | C20: =SUMIF(返済表!$B$4:$B$87,2,返済表!$D$4:$D$87) | D20: =SUMIF(返済表!$B$4:$B$87,3,返済表!$D$4:$D$87)
A21: 手元に残るお金（年） | B21: =B19-B20 | C21: =C19-C20 | D21: =D19-D20
A22: 手元に残るお金（月あたり） | B22: =ROUND(B21/12,0) | C22: =ROUND(C21/12,0) | D22: =ROUND(D21/12,0)
A23: 店主の生活費（月） | B23: =前提条件!$B$29 | C23: =前提条件!$B$29 | D23: =前提条件!$B$29
A24: 生活費をまかなえるか | B24: =IF(B22>=B23,"まかなえる","足りない") | C24: =IF(C22>=C23,"まかなえる","足りない") | D24: =IF(D22>=D23,"まかなえる","足りない")
A26: 損益分岐点（赤字にならないライン） | B26: 1年目 | C26: 2年目 | D26: 3年目
A27: 固定費（人件費・家賃・その他・償却・利息） | B27: =B8+B9+B11+B12+B13 | C27: =C8+C9+C11+C12+C13 | D27: =D8+D9+D11+D12+D13
A28: 変動費の割合（原価率＋水道光熱費） | B28: =前提条件!$B$11+前提条件!$B$15 | C28: =前提条件!$C$11+前提条件!$C$15 | D28: =前提条件!$D$11+前提条件!$D$15
A29: 損益分岐点の売上（年） | B29: =ROUND(B27/(1-B28),0) | C29: =ROUND(C27/(1-C28),0) | D29: =ROUND(D27/(1-D28),0)
A30: 1日あたり何人来れば黒字か | B30: =ROUNDUP(B29/12/(前提条件!$B$5+前提条件!$B$6)/((前提条件!$B$5*前提条件!$B$7*前提条件!$B$9+前提条件!$B$6*前提条件!$B$8*前提条件!$B$10)/(前提条件!$B$5*前提条件!$B$7+前提条件!$B$6*前提条件!$B$8)),0) | C30: =ROUNDUP(C29/12/(前提条件!$C$5+前提条件!$C$6)/((前提条件!$C$5*前提条件!$C$7*前提条件!$C$9+前提条件!$C$6*前提条件!$C$8*前提条件!$C$10)/(前提条件!$C$5*前提条件!$C$7+前提条件!$C$6*前提条件!$C$8)),0) | D30: =ROUNDUP(D29/12/(前提条件!$D$5+前提条件!$D$6)/((前提条件!$D$5*前提条件!$D$7*前提条件!$D$9+前提条件!$D$6*前提条件!$D$8*前提条件!$D$10)/(前提条件!$D$5*前提条件!$D$7+前提条件!$D$6*前提条件!$D$8)),0)
A31: 計画の1日の平均客数 | B31: =ROUND((前提条件!$B$5*前提条件!$B$7+前提条件!$B$6*前提条件!$B$8)/(前提条件!$B$5+前提条件!$B$6),0) | C31: =ROUND((前提条件!$C$5*前提条件!$C$7+前提条件!$C$6*前提条件!$C$8)/(前提条件!$C$5+前提条件!$C$6),0) | D31: =ROUND((前提条件!$D$5*前提条件!$D$7+前提条件!$D$6*前提条件!$D$8)/(前提条件!$D$5+前提条件!$D$6),0)

Sheet 1年目の月別
A1: 1年目の月別収支（開店 2027年4月）
A2: 季節の波：夏は冷たい飲み物で増え、2月は寒さで減る見込み（係数は黄色で変えられます）
A4: 項目 | B4: 4月 | C4: 5月 | D4: 6月 | E4: 7月 | F4: 8月 | G4: 9月 | H4: 10月 | I4: 11月 | J4: 12月 | K4: 1月 | L4: 2月 | M4: 3月 | N4: 1年目の合計
A5: 季節の係数 | B5: 1 | C5: 1.05 | D5: 0.95 | E5: 1.1 | F5: 1.1 | G5: 1 | H5: 1 | I5: 0.95 | J5: 1.05 | K5: 0.95 | L5: 0.85 | M5: 1 | N5: =SUM(B5:M5)
A6: 売上 | B6: =ROUND((前提条件!$B$5*前提条件!$B$7*前提条件!$B$9+前提条件!$B$6*前提条件!$B$8*前提条件!$B$10)*B5,0) | C6: =ROUND((前提条件!$B$5*前提条件!$B$7*前提条件!$B$9+前提条件!$B$6*前提条件!$B$8*前提条件!$B$10)*C5,0) | D6: =ROUND((前提条件!$B$5*前提条件!$B$7*前提条件!$B$9+前提条件!$B$6*前提条件!$B$8*前提条件!$B$10)*D5,0) | E6: =ROUND((前提条件!$B$5*前提条件!$B$7*前提条件!$B$9+前提条件!$B$6*前提条件!$B$8*前提条件!$B$10)*E5,0) | F6: =ROUND((前提条件!$B$5*前提条件!$B$7*前提条件!$B$9+前提条件!$B$6*前提条件!$B$8*前提条件!$B$10)*F5,0) | G6: =ROUND((前提条件!$B$5*前提条件!$B$7*前提条件!$B$9+前提条件!$B$6*前提条件!$B$8*前提条件!$B$10)*G5,0) | H6: =ROUND((前提条件!$B$5*前提条件!$B$7*前提条件!$B$9+前提条件!$B$6*前提条件!$B$8*前提条件!$B$10)*H5,0) | I6: =ROUND((前提条件!$B$5*前提条件!$B$7*前提条件!$B$9+前提条件!$B$6*前提条件!$B$8*前提条件!$B$10)*I5,0) | ... M6: =ROUND((前提条件!$B$5*前提条件!$B$7*前提条件!$B$9+前提条件!$B$6*前提条件!$B$8*前提条件!$B$10)*M5,0) | N6: =SUM(B6:M6)
A7: 材料費（原価） | B7: =ROUND(B6*前提条件!$B$11,0) | C7: =ROUND(C6*前提条件!$B$11,0) | D7: =ROUND(D6*前提条件!$B$11,0) | E7: =ROUND(E6*前提条件!$B$11,0) | F7: =ROUND(F6*前提条件!$B$11,0) | G7: =ROUND(G6*前提条件!$B$11,0) | H7: =ROUND(H6*前提条件!$B$11,0) | I7: =ROUND(I6*前提条件!$B$11,0) | ... M7: =ROUND(M6*前提条件!$B$11,0) | N7: =SUM(B7:M7)
A8: 粗利 | B8: =B6-B7 | C8: =C6-C7 | D8: =D6-D7 | E8: =E6-E7 | F8: =F6-F7 | G8: =G6-G7 | H8: =H6-H7 | I8: =I6-I7 | ... M8: =M6-M7 | N8: =SUM(B8:M8)
A9: アルバイト人件費 | B9: =前提条件!$B$12*前提条件!$B$13 | C9: =前提条件!$B$12*前提条件!$B$13 | D9: =前提条件!$B$12*前提条件!$B$13 | E9: =前提条件!$B$12*前提条件!$B$13 | F9: =前提条件!$B$12*前提条件!$B$13 | G9: =前提条件!$B$12*前提条件!$B$13 | H9: =前提条件!$B$12*前提条件!$B$13 | I9: =前提条件!$B$12*前提条件!$B$13 | ... M9: =前提条件!$B$12*前提条件!$B$13 | N9: =SUM(B9:M9)
A10: 家賃 | B10: =前提条件!$B$14 | C10: =前提条件!$B$14 | D10: =前提条件!$B$14 | E10: =前提条件!$B$14 | F10: =前提条件!$B$14 | G10: =前提条件!$B$14 | H10: =前提条件!$B$14 | I10: =前提条件!$B$14 | ... M10: =前提条件!$B$14 | N10: =SUM(B10:M10)
A11: 水道光熱費 | B11: =ROUND(B6*前提条件!$B$15,0) | C11: =ROUND(C6*前提条件!$B$15,0) | D11: =ROUND(D6*前提条件!$B$15,0) | E11: =ROUND(E6*前提条件!$B$15,0) | F11: =ROUND(F6*前提条件!$B$15,0) | G11: =ROUND(G6*前提条件!$B$15,0) | H11: =ROUND(H6*前提条件!$B$15,0) | I11: =ROUND(I6*前提条件!$B$15,0) | ... M11: =ROUND(M6*前提条件!$B$15,0) | N11: =SUM(B11:M11)
A12: その他の経費 | B12: =前提条件!$B$16 | C12: =前提条件!$B$16 | D12: =前提条件!$B$16 | E12: =前提条件!$B$16 | F12: =前提条件!$B$16 | G12: =前提条件!$B$16 | H12: =前提条件!$B$16 | I12: =前提条件!$B$16 | ... M12: =前提条件!$B$16 | N12: =SUM(B12:M12)
A13: 減価償却費 | B13: =ROUND('開業資金と調達'!$B$13/前提条件!$B$28/12,0) | C13: =ROUND('開業資金と調達'!$B$13/前提条件!$B$28/12,0) | D13: =ROUND('開業資金と調達'!$B$13/前提条件!$B$28/12,0) | E13: =ROUND('開業資金と調達'!$B$13/前提条件!$B$28/12,0) | F13: =ROUND('開業資金と調達'!$B$13/前提条件!$B$28/12,0) | G13: =ROUND('開業資金と調達'!$B$13/前提条件!$B$28/12,0) | H13: =ROUND('開業資金と調達'!$B$13/前提条件!$B$28/12,0) | I13: =ROUND('開業資金と調達'!$B$13/前提条件!$B$28/12,0) | ... M13: =ROUND('開業資金と調達'!$B$13/前提条件!$B$28/12,0) | N13: =SUM(B13:M13)
A14: 支払利息 | B14: =返済表!E4 | C14: =返済表!E5 | D14: =返済表!E6 | E14: =返済表!E7 | F14: =返済表!E8 | G14: =返済表!E9 | H14: =返済表!E10 | I14: =返済表!E11 | J14: =返済表!E12 | K14: =返済表!E13 | L14: =返済表!E14 | M14: =返済表!E15 | N14: =SUM(B14:M14)
A15: 経費の合計 | B15: =SUM(B9:B14) | C15: =SUM(C9:C14) | D15: =SUM(D9:D14) | E15: =SUM(E9:E14) | F15: =SUM(F9:F14) | G15: =SUM(G9:G14) | H15: =SUM(H9:H14) | I15: =SUM(I9:I14) | ... M15: =SUM(M9:M14) | N15: =SUM(B15:M15)
A16: 利益 | B16: =B8-B15 | C16: =C8-C15 | D16: =D8-D15 | E16: =E8-E15 | F16: =F8-F15 | G16: =G8-G15 | H16: =H8-H15 | I16: =I8-I15 | ... M16: =M8-M15 | N16: =SUM(B16:M16)

Sheet 開業資金と調達
A1: 開業資金と調達方法
A3: 何に使うか | B3: 金額 | D3: どこから用意するか | E3: 金額
A4: 物件取得費 | B4: =前提条件!$B$19 | D4: 自己資金 | E4: =前提条件!$B$24
A5: 内装工事 | B5: =前提条件!$B$20 | D5: 日本政策金融公庫からの借入 | E5: =前提条件!$B$25
A6: 厨房機器 | B6: =前提条件!$B$21
A7: 家具・食器などの備品 | B7: =前提条件!$B$22
A8: 運転資金 | B8: =前提条件!$B$23
A9: 合計 | B9: =SUM(B4:B8) | D9: 合計 | E9: =SUM(E4:E8)
A11: 使う額と用意する額の差（0ならぴったり） | B11: =E9-B9
A12: 自己資金の割合 | B12: =E4/E9
A13: 設備（償却する分） | B13: =B5+B6+B7

Sheet 返済表
A1: 借入の返済表（元金均等）
A3: 回 | B3: 年目 | C3: 月初の残高 | D3: 元金 | E3: 利息 | F3: 返済額 | G3: 月末の残高
A4: 1 | B4: =ROUNDUP(A4/12,0) | C4: =前提条件!$B$25 | D4: =IF(A4<=前提条件!$B$27,MIN(C4,ROUND(前提条件!$B$25/前提条件!$B$27,0)),0) | E4: =ROUND(C4*前提条件!$B$26/12,0) | F4: =D4+E4 | G4: =C4-D4
A5: 2 | B5: =ROUNDUP(A5/12,0) | C5: =G4 | D5: =IF(A5<=前提条件!$B$27,MIN(C5,ROUND(前提条件!$B$25/前提条件!$B$27,0)),0) | E5: =ROUND(C5*前提条件!$B$26/12,0) | F5: =D5+E5 | G5: =C5-D5
A6: 3 | B6: =ROUNDUP(A6/12,0) | C6: =G5 | D6: =IF(A6<=前提条件!$B$27,MIN(C6,ROUND(前提条件!$B$25/前提条件!$B$27,0)),0) | E6: =ROUND(C6*前提条件!$B$26/12,0) | F6: =D6+E6 | G6: =C6-D6
A7: 4 | B7: =ROUNDUP(A7/12,0) | C7: =G6 | D7: =IF(A7<=前提条件!$B$27,MIN(C7,ROUND(前提条件!$B$25/前提条件!$B$27,0)),0) | E7: =ROUND(C7*前提条件!$B$26/12,0) | F7: =D7+E7 | G7: =C7-D7
A8: 5 | B8: =ROUNDUP(A8/12,0) | C8: =G7 | D8: =IF(A8<=前提条件!$B$27,MIN(C8,ROUND(前提条件!$B$25/前提条件!$B$27,0)),0) | E8: =ROUND(C8*前提条件!$B$26/12,0) | F8: =D8+E8 | G8: =C8-D8
A9: 6 | B9: =ROUNDUP(A9/12,0) | C9: =G8 | D9: =IF(A9<=前提条件!$B$27,MIN(C9,ROUND(前提条件!$B$25/前提条件!$B$27,0)),0) | E9: =ROUND(C9*前提条件!$B$26/12,0) | F9: =D9+E9 | G9: =C9-D9
A10: 7 | B10: =ROUNDUP(A10/12,0) | C10: =G9 | D10: =IF(A10<=前提条件!$B$27,MIN(C10,ROUND(前提条件!$B$25/前提条件!$B$27,0)),0) | E10: =ROUND(C10*前提条件!$B$26/12,0) | F10: =D10+E10 | G10: =C10-D10
A11: 8 | B11: =ROUNDUP(A11/12,0) | C11: =G10 | D11: =IF(A11<=前提条件!$B$27,MIN(C11,ROUND(前提条件!$B$25/前提条件!$B$27,0)),0) | E11: =ROUND(C11*前提条件!$B$26/12,0) | F11: =D11+E11 | G11: =C11-D11
A12: 9 | B12: =ROUNDUP(A12/12,0) | C12: =G11 | D12: =IF(A12<=前提条件!$B$27,MIN(C12,ROUND(前提条件!$B$25/前提条件!$B$27,0)),0) | E12: =ROUND(C12*前提条件!$B$26/12,0) | F12: =D12+E12 | G12: =C12-D12
A13: 10 | B13: =ROUNDUP(A13/12,0) | C13: =G12 | D13: =IF(A13<=前提条件!$B$27,MIN(C13,ROUND(前提条件!$B$25/前提条件!$B$27,0)),0) | E13: =ROUND(C13*前提条件!$B$26/12,0) | F13: =D13+E13 | G13: =C13-D13
A14: 11 | B14: =ROUNDUP(A14/12,0) | C14: =G13 | D14: =IF(A14<=前提条件!$B$27,MIN(C14,ROUND(前提条件!$B$25/前提条件!$B$27,0)),0) | E14: =ROUND(C14*前提条件!$B$26/12,0) | F14: =D14+E14 | G14: =C14-D14
A15: 12 | B15: =ROUNDUP(A15/12,0) | C15: =G14 | D15: =IF(A15<=前提条件!$B$27,MIN(C15,ROUND(前提条件!$B$25/前提条件!$B$27,0)),0) | E15: =ROUND(C15*前提条件!$B$26/12,0) | F15: =D15+E15 | G15: =C15-D15
A16: 13 | B16: =ROUNDUP(A16/12,0) | C16: =G15 | D16: =IF(A16<=前提条件!$B$27,MIN(C16,ROUND(前提条件!$B$25/前提条件!$B$27,0)),0) | E16: =ROUND(C16*前提条件!$B$26/12,0) | F16: =D16+E16 | G16: =C16-D16
... A87: 84 | B87: =ROUNDUP(A87/12,0) | C87: =G86 | D87: =IF(A87<=前提条件!$B$27,MIN(C87,ROUND(前提条件!$B$25/前提条件!$B$27,0)),0) | E87: =ROUND(C87*前提条件!$B$26/12,0) | F87: =D87+E87 | G87: =C87-D87

Sheet グラフ
B1: グラフ（数字が変わると自動で描き直されます）
L2: グラフのもとの数字（万円）
L3: 年 | M3: 売上 | N3: 経費（原価含む） | O3: 利益
L4: 1年目 | M4: =ROUND('3年間の収支'!B5/10000,0) | N4: =ROUND(('3年間の収支'!B6+'3年間の収支'!B14)/10000,0) | O4: =ROUND('3年間の収支'!B15/10000,0)
L5: 2年目 | M5: =ROUND('3年間の収支'!C5/10000,0) | N5: =ROUND(('3年間の収支'!C6+'3年間の収支'!C14)/10000,0) | O5: =ROUND('3年間の収支'!C15/10000,0)
L6: 3年目 | M6: =ROUND('3年間の収支'!D5/10000,0) | N6: =ROUND(('3年間の収支'!D6+'3年間の収支'!D14)/10000,0) | O6: =ROUND('3年間の収支'!D15/10000,0)
L9: 月 | M9: 売上（万円） | N9: 利益（万円）
L10: 4月 | M10: =ROUND('1年目の月別'!B6/10000,1) | N10: =ROUND('1年目の月別'!B16/10000,1)
L11: 5月 | M11: =ROUND('1年目の月別'!C6/10000,1) | N11: =ROUND('1年目の月別'!C16/10000,1)
L12: 6月 | M12: =ROUND('1年目の月別'!D6/10000,1) | N12: =ROUND('1年目の月別'!D16/10000,1)
L13: 7月 | M13: =ROUND('1年目の月別'!E6/10000,1) | N13: =ROUND('1年目の月別'!E16/10000,1)
L14: 8月 | M14: =ROUND('1年目の月別'!F6/10000,1) | N14: =ROUND('1年目の月別'!F16/10000,1)
L15: 9月 | M15: =ROUND('1年目の月別'!G6/10000,1) | N15: =ROUND('1年目の月別'!G16/10000,1)
L16: 10月 | M16: =ROUND('1年目の月別'!H6/10000,1) | N16: =ROUND('1年目の月別'!H16/10000,1)
L17: 11月 | M17: =ROUND('1年目の月別'!I6/10000,1) | N17: =ROUND('1年目の月別'!I16/10000,1)
L18: 12月 | M18: =ROUND('1年目の月別'!J6/10000,1) | N18: =ROUND('1年目の月別'!J16/10000,1)
L19: 1月 | M19: =ROUND('1年目の月別'!K6/10000,1) | N19: =ROUND('1年目の月別'!K16/10000,1)
L20: 2月 | M20: =ROUND('1年目の月別'!L6/10000,1) | N20: =ROUND('1年目の月別'!L16/10000,1)
L21: 3月 | M21: =ROUND('1年目の月別'!M6/10000,1) | N21: =ROUND('1年目の月別'!M16/10000,1)
